{
    "repo_search": "Поиск репозитория",
    "repo": "Репозиторий",
    "language": "Язык",
    "to_main_page": "На главную страницу",
    "page_is_not_found": "Страница не найдена",
    "last_update": "Последнее изменение",
    "previous": "Предыдущая",
    "next": "Следующая",
    "search": "Поиск...",
    "owner": "Владелец",
    "top_contributors": "Топ контрибьютеров",
    "nothing_is_found": "Ничего не найдено",
    "contributions": "Личный вклад",
    "loading": "Загрузка...",
    "repos_found_approximately": "Найдено репозиториев: примерно",
    "error": "Ошибка",
    "fetching": "Получение данных...",
    "scroll_to_top": "Скролл вверх"
}
